commodutil/__init__.py
commodutil/arb.py
commodutil/convfactors.py
commodutil/dates.py
commodutil/forwards.py
commodutil/pandasutil.py
commodutil/stats.py
commodutil/transforms.py
commodutil/forward/__init__.py
commodutil/forward/calendar.py
commodutil/forward/continuous.py
commodutil/forward/fly.py
commodutil/forward/quarterly.py
commodutil/forward/spreads.py
commodutil/forward/structure.py
commodutil/forward/util.py
commodutil-3.0.0.dist-info/METADATA
commodutil-3.0.0.dist-info/WHEEL
commodutil-3.0.0.dist-info/top_level.txt
commodutil-3.0.0.dist-info/RECORD
